fog05/DLogger.py
fog05/__init__.py
fog05/fimapi.py
fog05/fimapi_rest.py
fog05-0.2.1.dist-info/LICENSE.md
fog05-0.2.1.dist-info/METADATA
fog05-0.2.1.dist-info/WHEEL
fog05-0.2.1.dist-info/top_level.txt
fog05-0.2.1.dist-info/RECORD
