Metadata-Version: 2.1
Name: fog05
Version: 0.2.1
Summary: Eclipse fog05 Client API
Home-page: https://fog05.io
Author: ADLINK
Author-email: gabriele.baldoni@adlinktech.com
License: Apache 2.O or EPL 2.0
Platform: UNKNOWN
Requires-Python: >=3
Requires-Dist: fog05-sdk (==0.2.1)
Requires-Dist: yaks (==0.3.0.post1)
Requires-Dist: jsonschema
Requires-Dist: mvar (==0.0.1)
